hanK_pki.py
setup.py
hanK_pki.egg-info/PKG-INFO
hanK_pki.egg-info/SOURCES.txt
hanK_pki.egg-info/dependency_links.txt
hanK_pki.egg-info/requires.txt
hanK_pki.egg-info/top_level.txt