Metadata-Version: 1.0
Name: hanK-pki
Version: 0.0.4
Summary: Korea NPKI Auth Module
Home-page: UNKNOWN
Author: hanjungwook
Author-email: hjw0652@gmail.com
License: UNKNOWN
Platform: UNKNOWN
